Workbook

Sheet Mode d'emploi
A1: Vocabulaire d'anglais — A1 à B2
A3: Ce tableur accompagne le document « Cours d'anglais — contenus complets A1 à B2 ».
A5: Onglets
A6: Résumé : nombre de mots par niveau, par module et par catégorie de l'appli (calculé automatiquement).
A7: A1, A2, B1, B2 : le vocabulaire de chaque niveau, rangé par module.
A8: Tout le vocabulaire : la liste complète en un seul tableau, prête à importer dans l'appli (export CSV possible).
A10: Colonnes
A11: ID : identifiant unique du mot (utile pour l'import dans Firestore).
A12: Niveau / Module / Thème : où le mot est étudié dans le programme.
A13: Anglais / Français : recto et verso de la carte.
A14: Nature : nom, verbe, adj (adjectif), adv (adverbe), expr (expression), prép (préposition), conj (conjonction), pron (pronom), nombre.
A15: Catégorie appli : Débutant, Voyage, Sport, Technique ou Général (pour les paquets de cartes et le jeu Words).
... A19: Les verbes sont notés avec « to » (to run) ; les mots qui ont deux sens apparaissent deux fois avec leur sens (left = gauche / parti).

Sheet Résumé
A1: Résumé du vocabulaire
A3: Par niveau
A4: Niveau | B4: Nombre de mots
A5: A1 | B5: =COUNTIF('Tout le vocabulaire'!$B$2:$B$956,A5) -> 237
A6: A2 | B6: =COUNTIF('Tout le vocabulaire'!$B$2:$B$956,A6) -> 233
A7: B1 | B7: =COUNTIF('Tout le vocabulaire'!$B$2:$B$956,A7) -> 246
A8: B2 | B8: =COUNTIF('Tout le vocabulaire'!$B$2:$B$956,A8) -> 239
A9: Total | B9: =SUM(B5:B8) -> 955
A11: Par module
A12: Niveau | B12: Module | C12: Thème | D12: Nombre de mots
A13: A1 | B13: 1 | C13: Moi et les autres | D13: =COUNTIFS('Tout le vocabulaire'!$B$2:$B$956,A13,'Tout le vocabulaire'!$C$2:$C$956,B13) -> 80
A14: A1 | B14: 2 | C14: Mon quotidien | D14: =COUNTIFS('Tout le vocabulaire'!$B$2:$B$956,A14,'Tout le vocabulaire'!$C$2:$C$956,B14) -> 82
A15: A1 | B15: 3 | C15: Autour de moi | D15: =COUNTIFS('Tout le vocabulaire'!$B$2:$B$956,A15,'Tout le vocabulaire'!$C$2:$C$956,B15) -> 75
A16: A2 | B16: 4 | C16: Ce qui se passe maintenant | D16: =COUNTIFS('Tout le vocabulaire'!$B$2:$B$956,A16,'Tout le vocabulaire'!$C$2:$C$956,B16) -> 60
A17: A2 | B17: 5 | C17: Raconter le passé | D17: =COUNTIFS('Tout le vocabulaire'!$B$2:$B$956,A17,'Tout le vocabulaire'!$C$2:$C$956,B17) -> 54
A18: A2 | B18: 6 | C18: En voyage | D18: =COUNTIFS('Tout le vocabulaire'!$B$2:$B$956,A18,'Tout le vocabulaire'!$C$2:$C$956,B18) -> 62
A19: A2 | B19: 7 | C19: Comparer et décrire | D19: =COUNTIFS('Tout le vocabulaire'!$B$2:$B$956,A19,'Tout le vocabulaire'!$C$2:$C$956,B19) -> 57
A20: B1 | B20: 8 | C20: Expériences | D20: =COUNTIFS('Tout le vocabulaire'!$B$2:$B$956,A20,'Tout le vocabulaire'!$C$2:$C$956,B20) -> 38
A21: B1 | B21: 9 | C21: Raconter une histoire | D21: =COUNTIFS('Tout le vocabulaire'!$B$2:$B$956,A21,'Tout le vocabulaire'!$C$2:$C$956,B21) -> 39
A22: B1 | B22: 10 | C22: Hypothèses | D22: =COUNTIFS('Tout le vocabulaire'!$B$2:$B$956,A22,'Tout le vocabulaire'!$C$2:$C$956,B22) -> 38
A23: B1 | B23: 11 | C23: Le monde du travail | D23: =COUNTIFS('Tout le vocabulaire'!$B$2:$B$956,A23,'Tout le vocabulaire'!$C$2:$C$956,B23) -> 46
A24: B1 | B24: 12 | C24: Donner son avis | D24: =COUNTIFS('Tout le vocabulaire'!$B$2:$B$956,A24,'Tout le vocabulaire'!$C$2:$C$956,B24) -> 40
... A32: B2 | B32: 20 | C32: Bilan B2 et examen | D32: =COUNTIFS('Tout le vocabulaire'!$B$2:$B$956,A32,'Tout le vocabulaire'!$C$2:$C$956,B32) -> 21
A34: Par catégorie de l'appli
A35: Catégorie | B35: Nombre de mots
A36: Débutant | B36: =COUNTIF('Tout le vocabulaire'!$H$2:$H$956,A36) -> 326
A37: Voyage | B37: =COUNTIF('Tout le vocabulaire'!$H$2:$H$956,A37) -> 92
A38: Sport | B38: =COUNTIF('Tout le vocabulaire'!$H$2:$H$956,A38) -> 55
A39: Technique | B39: =COUNTIF('Tout le vocabulaire'!$H$2:$H$956,A39) -> 222
A40: Général | B40: =COUNTIF('Tout le vocabulaire'!$H$2:$H$956,A40) -> 260

Sheet A1
A1: ID | B1: Niveau | C1: Module | D1: Thème | E1: Anglais | F1: Français | G1: Nature | H1: Catégorie appli
A2: V0001 | B2: A1 | C2: 1 | D2: Moi et les autres | E2: hello | F2: bonjour, salut | G2: expr | H2: Débutant
A3: V0002 | B3: A1 | C3: 1 | D3: Moi et les autres | E3: hi | F3: salut | G3: expr | H3: Débutant
A4: V0003 | B4: A1 | C4: 1 | D4: Moi et les autres | E4: good morning | F4: bonjour (le matin) | G4: expr | H4: Débutant
A5: V0004 | B5: A1 | C5: 1 | D5: Moi et les autres | E5: good afternoon | F5: bonjour (l'après-midi) | G5: expr | H5: Débutant
A6: V0005 | B6: A1 | C6: 1 | D6: Moi et les autres | E6: good evening | F6: bonsoir | G6: expr | H6: Débutant
A7: V0006 | B7: A1 | C7: 1 | D7: Moi et les autres | E7: good night | F7: bonne nuit | G7: expr | H7: Débutant
A8: V0007 | B8: A1 | C8: 1 | D8: Moi et les autres | E8: goodbye | F8: au revoir | G8: expr | H8: Débutant
A9: V0008 | B9: A1 | C9: 1 | D9: Moi et les autres | E9: see you later | F9: à plus tard | G9: expr | H9: Débutant
A10: V0009 | B10: A1 | C10: 1 | D10: Moi et les autres | E10: please | F10: s'il te plaît, s'il vous plaît | G10: expr | H10: Débutant
A11: V0010 | B11: A1 | C11: 1 | D11: Moi et les autres | E11: thank you | F11: merci | G11: expr | H11: Débutant
A12: V0011 | B12: A1 | C12: 1 | D12: Moi et les autres | E12: you're welcome | F12: de rien | G12: expr | H12: Débutant
A13: V0012 | B13: A1 | C13: 1 | D13: Moi et les autres | E13: sorry | F13: désolé, pardon | G13: expr | H13: Débutant
... A238: V0237 | B238: A1 | C238: 3 | D238: Autour de moi | E238: to close | F238: fermer | G238: verbe | H238: Débutant

Sheet A2
A1: ID | B1: Niveau | C1: Module | D1: Thème | E1: Anglais | F1: Français | G1: Nature | H1: Catégorie appli
A2: V0238 | B2: A2 | C2: 4 | D2: Ce qui se passe maintenant | E2: hobby | F2: loisir, passe-temps | G2: nom | H2: Débutant
A3: V0239 | B3: A2 | C3: 4 | D3: Ce qui se passe maintenant | E3: free time | F3: temps libre | G3: nom | H3: Débutant
A4: V0240 | B4: A2 | C4: 4 | D4: Ce qui se passe maintenant | E4: to read | F4: lire | G4: verbe | H4: Débutant
A5: V0241 | B5: A2 | C5: 4 | D5: Ce qui se passe maintenant | E5: to listen to music | F5: écouter de la musique | G5: verbe | H5: Débutant
A6: V0242 | B6: A2 | C6: 4 | D6: Ce qui se passe maintenant | E6: to watch a film | F6: regarder un film | G6: verbe | H6: Débutant
A7: V0243 | B7: A2 | C7: 4 | D7: Ce qui se passe maintenant | E7: to play video games | F7: jouer aux jeux vidéo | G7: verbe | H7: Débutant
A8: V0244 | B8: A2 | C8: 4 | D8: Ce qui se passe maintenant | E8: to draw | F8: dessiner | G8: verbe | H8: Débutant
A9: V0245 | B9: A2 | C9: 4 | D9: Ce qui se passe maintenant | E9: to paint | F9: peindre | G9: verbe | H9: Débutant
A10: V0246 | B10: A2 | C10: 4 | D10: Ce qui se passe maintenant | E10: to dance | F10: danser | G10: verbe | H10: Débutant
A11: V0247 | B11: A2 | C11: 4 | D11: Ce qui se passe maintenant | E11: to sing | F11: chanter | G11: verbe | H11: Débutant
A12: V0248 | B12: A2 | C12: 4 | D12: Ce qui se passe maintenant | E12: to travel | F12: voyager | G12: verbe | H12: Voyage
A13: V0249 | B13: A2 | C13: 4 | D13: Ce qui se passe maintenant | E13: to go out | F13: sortir | G13: verbe | H13: Débutant
... A234: V0470 | B234: A2 | C234: 7 | D234: Comparer et décrire | E234: discount | F234: réduction | G234: nom | H234: Voyage

Sheet B1
A1: ID | B1: Niveau | C1: Module | D1: Thème | E1: Anglais | F1: Français | G1: Nature | H1: Catégorie appli
A2: V0471 | B2: B1 | C2: 8 | D2: Expériences | E2: experience | F2: expérience | G2: nom | H2: Général
A3: V0472 | B3: B1 | C3: 8 | D3: Expériences | E3: achievement | F3: réussite, accomplissement | G3: nom | H3: Général
A4: V0473 | B4: B1 | C4: 8 | D4: Expériences | E4: goal | F4: objectif | G4: nom | H4: Général
A5: V0474 | B5: B1 | C5: 8 | D5: Expériences | E5: challenge | F5: défi | G5: nom | H5: Général
A6: V0475 | B6: B1 | C6: 8 | D6: Expériences | E6: skill | F6: compétence | G6: nom | H6: Général
A7: V0476 | B7: B1 | C7: 8 | D7: Expériences | E7: degree | F7: diplôme (universitaire) | G7: nom | H7: Général
A8: V0477 | B8: B1 | C8: 8 | D8: Expériences | E8: master's degree | F8: master | G8: nom | H8: Général
A9: V0478 | B9: B1 | C9: 8 | D9: Expériences | E9: apprenticeship | F9: apprentissage, alternance | G9: nom | H9: Technique
A10: V0479 | B10: B1 | C10: 8 | D10: Expériences | E10: internship | F10: stage | G10: nom | H10: Technique
A11: V0480 | B11: B1 | C11: 8 | D11: Expériences | E11: abroad | F11: à l'étranger | G11: adv | H11: Voyage
A12: V0481 | B12: B1 | C12: 8 | D12: Expériences | E12: to apply for | F12: postuler à | G12: verbe | H12: Technique
A13: V0482 | B13: B1 | C13: 8 | D13: Expériences | E13: to succeed | F13: réussir | G13: verbe | H13: Général
... A247: V0716 | B247: B1 | C247: 13 | D247: Bilan B1 et technique de base | E247: width | F247: largeur | G247: nom | H247: Technique

Sheet B2
A1: ID | B1: Niveau | C1: Module | D1: Thème | E1: Anglais | F1: Français | G1: Nature | H1: Catégorie appli
A2: V0717 | B2: B2 | C2: 14 | D2: Le passé en détail | E2: background | F2: parcours, contexte | G2: nom | H2: Technique
A3: V0718 | B3: B2 | C3: 14 | D3: Le passé en détail | E3: career path | F3: parcours professionnel | G3: nom | H3: Technique
A4: V0719 | B4: B2 | C4: 14 | D4: Le passé en détail | E4: feedback | F4: retour, avis | G4: nom | H4: Technique
A5: V0720 | B5: B2 | C5: 14 | D5: Le passé en détail | E5: lessons learned | F5: retour d'expérience | G5: expr | H5: Technique
A6: V0721 | B6: B2 | C6: 14 | D6: Le passé en détail | E6: milestone | F6: jalon, étape clé | G6: nom | H6: Technique
A7: V0722 | B7: B2 | C7: 14 | D7: Le passé en détail | E7: timeline | F7: calendrier, chronologie | G7: nom | H7: Technique
A8: V0723 | B8: B2 | C8: 14 | D8: Le passé en détail | E8: delay | F8: retard | G8: nom | H8: Technique
A9: V0724 | B9: B2 | C9: 14 | D9: Le passé en détail | E9: to be delayed | F9: être retardé | G9: expr | H9: Technique
A10: V0725 | B10: B2 | C10: 14 | D10: Le passé en détail | E10: setback | F10: revers, contretemps | G10: nom | H10: Technique
A11: V0726 | B11: B2 | C11: 14 | D11: Le passé en détail | E11: shortage | F11: pénurie | G11: nom | H11: Technique
A12: V0727 | B12: B2 | C12: 14 | D12: Le passé en détail | E12: out of stock | F12: en rupture de stock | G12: expr | H12: Technique
A13: V0728 | B13: B2 | C13: 14 | D13: Le passé en détail | E13: bottleneck | F13: goulot d'étranglement | G13: nom | H13: Technique
... A240: V0955 | B240: B2 | C240: 20 | D240: Bilan B2 et examen | E240: weak point | F240: point faible | G240: nom | H240: Général

Sheet Tout le vocabulaire
A1: ID | B1: Niveau | C1: Module | D1: Thème | E1: Anglais | F1: Français | G1: Nature | H1: Catégorie appli
A2: V0001 | B2: A1 | C2: 1 | D2: Moi et les autres | E2: hello | F2: bonjour, salut | G2: expr | H2: Débutant
A3: V0002 | B3: A1 | C3: 1 | D3: Moi et les autres | E3: hi | F3: salut | G3: expr | H3: Débutant
A4: V0003 | B4: A1 | C4: 1 | D4: Moi et les autres | E4: good morning | F4: bonjour (le matin) | G4: expr | H4: Débutant
A5: V0004 | B5: A1 | C5: 1 | D5: Moi et les autres | E5: good afternoon | F5: bonjour (l'après-midi) | G5: expr | H5: Débutant
A6: V0005 | B6: A1 | C6: 1 | D6: Moi et les autres | E6: good evening | F6: bonsoir | G6: expr | H6: Débutant
A7: V0006 | B7: A1 | C7: 1 | D7: Moi et les autres | E7: good night | F7: bonne nuit | G7: expr | H7: Débutant
A8: V0007 | B8: A1 | C8: 1 | D8: Moi et les autres | E8: goodbye | F8: au revoir | G8: expr | H8: Débutant
A9: V0008 | B9: A1 | C9: 1 | D9: Moi et les autres | E9: see you later | F9: à plus tard | G9: expr | H9: Débutant
A10: V0009 | B10: A1 | C10: 1 | D10: Moi et les autres | E10: please | F10: s'il te plaît, s'il vous plaît | G10: expr | H10: Débutant
A11: V0010 | B11: A1 | C11: 1 | D11: Moi et les autres | E11: thank you | F11: merci | G11: expr | H11: Débutant
A12: V0011 | B12: A1 | C12: 1 | D12: Moi et les autres | E12: you're welcome | F12: de rien | G12: expr | H12: Débutant
A13: V0012 | B13: A1 | C13: 1 | D13: Moi et les autres | E13: sorry | F13: désolé, pardon | G13: expr | H13: Débutant
... A956: V0955 | B956: B2 | C956: 20 | D956: Bilan B2 et examen | E956: weak point | F956: point faible | G956: nom | H956: Général
